nebula_aws/__init__.py
nebula_aws/_version.py
nebula_aws/batch.py
nebula_aws/client_parameters.py
nebula_aws/client_waiter.py
nebula_aws/credentials.py
nebula_aws/ecs.py
nebula_aws/lambda_function.py
nebula_aws/s3.py
nebula_aws/secrets_manager.py
nebula_aws/utilities.py
nebula_aws/deployments/__init__.py
nebula_aws/deployments/steps.py
nebula_aws/workers/__init__.py
nebula_aws/workers/ecs_worker.py
nebula_aws-1.0.0.dist-info/LICENSE
nebula_aws-1.0.0.dist-info/METADATA
nebula_aws-1.0.0.dist-info/WHEEL
nebula_aws-1.0.0.dist-info/entry_points.txt
nebula_aws-1.0.0.dist-info/top_level.txt
nebula_aws-1.0.0.dist-info/RECORD
