Metadata-Version: 2.1
Name: nebula-aws
Version: 1.0.0
Summary: Nebula collection of tasks and subflows to integrate with AWS
Home-page: https://github.com/kozmoai/nebula-aws
Author: Kozmoai, Inc.
Author-email: help@nebula.io
License: Apache License 2.0
Keywords: nebula
Classifier: Natural Language :: English
Classifier: Intended Audience :: Developers
Classifier: Intended Audience :: System Administrators
Classifier: License :: OSI Approved :: Apache Software License
Classifier: Programming Language :: Python :: 3 :: Only
Classifier: Programming Language :: Python :: 3.7
Classifier: Programming Language :: Python :: 3.8
Classifier: Programming Language :: Python :: 3.9
Classifier: Programming Language :: Python :: 3.10
Classifier: Topic :: Software Development :: Libraries
Requires-Python: >=3.7
License-File: LICENSE
Requires-Dist: boto3 >=1.24.53
Requires-Dist: botocore >=1.27.53
Requires-Dist: mypy-boto3-s3 >=1.24.94
Requires-Dist: mypy-boto3-secretsmanager >=1.26.49
Requires-Dist: nebulaconsole >=1.0.0
Requires-Dist: tenacity >=8.0.0
Provides-Extra: dev
Requires-Dist: black ; extra == 'dev'
Requires-Dist: boto3-stubs >=1.24.39 ; extra == 'dev'
Requires-Dist: coverage ; extra == 'dev'
Requires-Dist: flake8 ; extra == 'dev'
Requires-Dist: interrogate ; extra == 'dev'
Requires-Dist: isort ; extra == 'dev'
Requires-Dist: mkdocs ; extra == 'dev'
Requires-Dist: mkdocs-gen-files ; extra == 'dev'
Requires-Dist: mkdocs-material ; extra == 'dev'
Requires-Dist: mkdocstrings-python-legacy ; extra == 'dev'
Requires-Dist: moto <4.2.5,>=3.1.16 ; extra == 'dev'
Requires-Dist: mypy ; extra == 'dev'
Requires-Dist: pillow ; extra == 'dev'
Requires-Dist: pre-commit ; extra == 'dev'
Requires-Dist: pytest ; extra == 'dev'
Requires-Dist: pytest-asyncio !=0.22.0,<0.23.0,>=0.18.2 ; extra == 'dev'
Requires-Dist: pytest-cov ; extra == 'dev'
Requires-Dist: pytest-xdist ; extra == 'dev'
Requires-Dist: types-boto3 >=1.0.2 ; extra == 'dev'
Requires-Dist: griffe ; extra == 'dev'
Requires-Dist: mock ; (python_version < "3.8") and extra == 'dev'
